Metadata-Version: 1.1
Name: gexml
Version: 1.2.0
Summary: A dead-simple Object-XML mapper for Python.
Home-page: https://github.com/ampledata/gexml
Author: Ryan Kelly
Author-email: oss@undef.net
License: Copyright (c) 2009-2011 Ryan Kelly
